{"subject":"BER",
"name":"Bergsprängning",
"points":200,
"requirements":"anläggning 2",
"instructiontext":"som bygger på kursen anläggning 2.",
"code":"BERBEP0",
"goaltext":"Kursen bergsprängning omfattar punkterna 1&mdash;10 under rubriken Ämnets syfte.",
"goals":[1,1,1,1,1,1,1,1,1,1],
"level":"normal",
"content":["Informationssökning för arbetsuppgiften med hjälp av internet och på andra sätt.",
"Planeringar och beräkningar för att lösa arbetsuppgifterna.",
"Bergarbete och berghantering. ",
"Kastrisker och täckningsmetoder.",
"Felsökning i sprängsalvor.",
"Sprängjournaler samt hantering av sprängämnen.",
"Olika typer av material och deras egenskaper.",
"Verktyg och maskiner för olika ändamål. Handhavande och skötsel.",
"Lagar och andra bestämmelser om hantering av sprängämnen, arbetsmiljö, hälsa och säkerhet. Ergonomiskt arbetssätt.",
"Sprängämnen och sprängningsarbeten ur ett risk- och säkerhetsperspektiv. Riskbedömningar vid sprängningsarbeten.",
"Problemlösning i samband med arbetsuppgifterna.",
"Metoder för att utvärdera sitt arbete.",
"Hållbart byggande. Hantering av material, till exempel förvaring, minimering av spill samt sortering av byggavfall och restprodukter. Resursanvändande kopplat till arbetsuppgiften.",
"Facktermer i relation till arbetsuppgiften."]}