{"subject":"FLY",
"novux":false,
"name":"Flygplanslära",
"origname":"Flygplanslära",
"points":200,
"code":"FLYFLG0",
"goals":[0,1,0,1,1,1,1,1,0],
"excludesgoals":true,
"focusesgoals":false,
"level":"normal",
"content":["Service- och underhållsåtgärder av flygplan och propellrar.",
"Flygplans olika system och konstruktionsprinciper samt påfrestningar som flygplan utsätts för i olika flygsituationer.",
"Flygplans aerodynamik och styrorgan.",
"Flygplanskonstruktioner, till exempel skrovkonstruktioner och konstruktionsmetoder.",
"Luftkonditionering och trycksättning av kabin.",
"Instrument- och avioniksystem.",
"Flygplans elkraftförsörjning.",
"Utrustning och inventarier i flygplan, till exempel kabinutformning, instigningsanordningar och nödutrustning.",
"Brandsläckningssystem.",
"Styrsystem.",
"Bränslesystem.",
"Hydrauliksystem.",
"Is- och regnskydd på flygplan och propellrar.",
"Landställs uppbyggnad och funktion.",
"Ljus, strålkastare och belysning.",
"Systemutformning för syrgas i cockpit och kabin.",
"Pneumatik och vakuum, till exempel kompressorer och tryckreglering.",
"Vatten och avlopp, till exempel utformning av toalett och vattensystem.",
"Flygburna underhållssystem, till exempel centrala underhållsdatorer och elektroniskt arkivsystem.",
"Propellrars konstruktion, till exempel aerodynamisk belastning och material.",
"Reglering av propellerbladvinkel och propellersynkronisering."],
"judgeraw":"<h4>Betyget E</h4><p>Eleven beskriver <b>översiktligt</b> med stöd av informationsmaterial konstruktion av, funktion hos och påfrestningar på flygplan och deras olika system. Dessutom beskriver eleven <b>översiktligt</b> med stöd av informationsmaterial hur flygplanets olika system är integrerade och samverkar med varandra.</p><p>Eleven utför <b>i samråd</b> med handledare och i bekanta situatione <b>enkel</b> service och <b>enkla</b> underhållsåtgärder av flygplan och propellrar. Dessutom utför eleven <b>i samråd</b> med handledare felsökning och åtgärdar <b>enkla</b> fel på flygplanets olika system enligt regelverk och kvalitetskrav. Eleven arbetar i bekanta situationer utifrån de instruktioner och det regelverk som uppgiften kräver. När arbetet är utfört utvärderar eleven med <b>enkla</b> omdömen sina arbetsprocesser och sitt resultat. Dessutom gör eleven en <b>enkel</b> dokumentation av sitt arbete.</p><p>Eleven kommunicerar med ett <b>enkelt</b> <b>men</b> för arbetsuppgiften fungerande fackspråk. Dessutom samarbetar eleven för att nå planerade resultat. Resultatet av elevens arbete är <b>tillfredsställande</b>.</p><p>När eleven samråder med handledare bedömer hon eller han <b>med viss säkerhet</b> den egna förmågan och situationens krav.</p>                     <h4>Betyget D</h4><p>Betyget D innebär att kunskapskraven för E och till övervägande del för C är uppfyllda.</p>                     <h4>Betyget C</h4><p>Eleven beskriver <b>utförligt</b> med stöd av informationsmaterial konstruktion av, funktion hos och påfrestningar på flygplan och deras olika system. Dessutom beskriver eleven <b>utförligt</b> med stöd av informationsmaterial hur flygplanets olika system är integrerade och samverkar med varandra.</p><p>Eleven utför <b>efter samråd</b> med handledare och i bekanta <b>och delvis nya</b> situationer service och underhållsåtgärder av flygplan och propellrar. Dessutom utför eleven <b>efter samråd</b> med handledare felsökning och åtgärdar fel på flygplanets olika system enligt regelverk och kvalitetskrav. Eleven arbetar i bekanta <b>och delvis nya</b> situationer utifrån de instruktioner och det regelverk som uppgiften kräver. När arbetet är utfört utvärderar eleven med <b>nyanserade</b> omdömen sina arbetsprocesser och sitt resultat. Dessutom gör eleven en <b>noggrann</b> dokumentation av sitt arbete.</p><p>Eleven kommunicerar med ett för arbetsuppgiften fungerande fackspråk. Dessutom samarbetar eleven <b>och medverkar till att upprätthålla samarbetet</b> för att nå planerade resultat. Resultatet av elevens arbete är <b>tillfredsställande</b>.</p><p>När eleven samråder med handledare bedömer hon eller han <b>med viss säkerhet</b> den egna förmågan och situationens krav.</p>                     <h4>Betyget B</h4><p>Betyget B innebär att kunskapskraven för C och till övervägande del för A är uppfyllda.</p>                     <h4>Betyget A</h4><p>Eleven beskriver <b>utförligt och nyanserat</b> med stöd av informationsmaterial konstruktion av, funktion hos och påfrestningar på flygplan och deras olika system. Dessutom beskriver eleven <b>utförligt och nyanserat</b> med stöd av informationsmaterial hur flygplanets olika system är integrerade och samverkar med varandra.</p><p>Eleven utför <b>efter samråd</b> med handledare och i bekanta <b>och nya</b> situationer service och underhållsåtgärder av flygplan och propellrar. Dessutom utför eleven <b>efter samråd</b> med handledare felsökning och åtgärdar <b>komplexa</b> fel på flygplanets olika system enligt regelverk och kvalitetskrav. Eleven arbetar i bekanta <b>och nya</b> situationer utifrån de instruktioner och det regelverk som uppgiften kräver. När arbetet är utfört utvärderar eleven med <b>nyanserade</b> omdömen sina arbetsprocesser och sitt resultat <b>samt ger förslag på hur arbetet kan förbättras</b>. Dessutom gör eleven en <b>noggrann och utförlig</b> dokumentation av sitt arbete.</p><p>Eleven kommunicerar med ett <b>nyanserat och</b> för arbetsuppgiften fungerande fackspråk. Dessutom samarbetar eleven <b>och medverkar till att upprätthålla och utveckla samarbetet</b> för att nå planerade resultat. Resultatet av elevens arbete är <b>gott</b>.</p><p>När eleven samråder med handledare bedömer hon eller han <b>med säkerhet</b> den egna förmågan och situationens krav.</p>",
"judge":{"E":["Eleven beskriver <b>översiktligt</b> med stöd av informationsmaterial konstruktion av, funktion hos och påfrestningar på flygplan och deras olika system. Dessutom beskriver eleven <b>översiktligt</b> med stöd av informationsmaterial hur flygplanets olika system är integrerade och samverkar med varandra.",
"Eleven utför <b>i samråd</b> med handledare och i bekanta situatione <b>enkel</b> service och <b>enkla</b> underhållsåtgärder av flygplan och propellrar. Dessutom utför eleven <b>i samråd</b> med handledare felsökning och åtgärdar <b>enkla</b> fel på flygplanets olika system enligt regelverk och kvalitetskrav. Eleven arbetar i bekanta situationer utifrån de instruktioner och det regelverk som uppgiften kräver. När arbetet är utfört utvärderar eleven med <b>enkla</b> omdömen sina arbetsprocesser och sitt resultat. Dessutom gör eleven en <b>enkel</b> dokumentation av sitt arbete.",
"Eleven kommunicerar med ett <b>enkelt</b> <b>men</b> för arbetsuppgiften fungerande fackspråk. Dessutom samarbetar eleven för att nå planerade resultat. Resultatet av elevens arbete är <b>tillfredsställande</b>.",
"När eleven samråder med handledare bedömer hon eller han <b>med viss säkerhet</b> den egna förmågan och situationens krav."],
"C":["Eleven beskriver <b>utförligt</b> med stöd av informationsmaterial konstruktion av, funktion hos och påfrestningar på flygplan och deras olika system. Dessutom beskriver eleven <b>utförligt</b> med stöd av informationsmaterial hur flygplanets olika system är integrerade och samverkar med varandra.",
"Eleven utför <b>efter samråd</b> med handledare och i bekanta <b>och delvis nya</b> situationer service och underhållsåtgärder av flygplan och propellrar. Dessutom utför eleven <b>efter samråd</b> med handledare felsökning och åtgärdar fel på flygplanets olika system enligt regelverk och kvalitetskrav. Eleven arbetar i bekanta <b>och delvis nya</b> situationer utifrån de instruktioner och det regelverk som uppgiften kräver. När arbetet är utfört utvärderar eleven med <b>nyanserade</b> omdömen sina arbetsprocesser och sitt resultat. Dessutom gör eleven en <b>noggrann</b> dokumentation av sitt arbete.",
"Eleven kommunicerar med ett för arbetsuppgiften fungerande fackspråk. Dessutom samarbetar eleven <b>och medverkar till att upprätthålla samarbetet</b> för att nå planerade resultat. Resultatet av elevens arbete är <b>tillfredsställande</b>.",
"När eleven samråder med handledare bedömer hon eller han <b>med viss säkerhet</b> den egna förmågan och situationens krav."],
"A":["Eleven beskriver <b>utförligt och</b> <b>nyanserat</b> med stöd av informationsmaterial konstruktion av, funktion hos och påfrestningar på flygplan och deras olika system. Dessutom beskriver eleven <b>utförligt och</b> <b>nyanserat</b> med stöd av informationsmaterial hur flygplanets olika system är integrerade och samverkar med varandra.",
"Eleven utför <b>efter samråd</b> med handledare och i bekanta <b>och nya</b> situationer service och underhållsåtgärder av flygplan och propellrar. Dessutom utför eleven <b>efter samråd</b> med handledare felsökning och åtgärdar <b>komplexa</b> fel på flygplanets olika system enligt regelverk och kvalitetskrav. Eleven arbetar i bekanta <b>och nya</b> situationer utifrån de instruktioner och det regelverk som uppgiften kräver. När arbetet är utfört utvärderar eleven med <b>nyanserade</b> omdömen sina arbetsprocesser och sitt resultat <b>samt ger förslag på hur arbetet kan förbättras</b>. Dessutom gör eleven en <b>noggrann och utförlig</b> dokumentation av sitt arbete.",
"Eleven kommunicerar med ett <b>nyanserat och</b> för arbetsuppgiften fungerande fackspråk. Dessutom samarbetar eleven <b>och medverkar till att upprätthålla och utveckla samarbetet</b> för att nå planerade resultat. Resultatet av elevens arbete är <b>gott</b>.",
"När eleven samråder med handledare bedömer hon eller han <b>med säkerhet</b> den egna förmågan och situationens krav."]},
"friends":["FLYAER0",
"FLYDII0",
"FLYELT0",
"FLYELL0",
"FLYFLY0",
"FLYGAT0",
"FLYHEL0",
"FLYKOL0",
"FLYMAA0",
"FLYMAS0",
"FLYUNS0"]}